grapphy/__init__.py
grapphy/edge_cover.py
grapphy/graph_utils.py
grapphy/flow/__init__.py
grapphy/special_graphs/__init__.py
grapphy/special_graphs/trigraph.py
grapphy/traversal/__init__.py
grapphy/traversal/dfs.py
grapphy/traversal/walks.py
grapphy/use_cases/__init__.py
grapphy/use_cases/assignment_like.py
grapphy/use_cases/sports_elimintn.py
grapphy-0.0.0.dist-info/LICENSE
grapphy-0.0.0.dist-info/METADATA
grapphy-0.0.0.dist-info/WHEEL
grapphy-0.0.0.dist-info/top_level.txt
grapphy-0.0.0.dist-info/RECORD
